rtl/cpu_pipeline.v
`timescale 1ns/1ps

module cpu_pipeline(input clk);

reg [31:0] imem [0:255];
reg [31:0] dmem [0:255];
reg [31:0] regs [0:31];

integer i;
initial begin
for(i=0;i<32;i=i+1)
regs[i]=0;
end

integer j;
initial begin
for(j=0;j<256;j=j+1)
dmem[j]=0;
end

reg [31:0] pc=0;

reg [31:0] IF_ID_instr=0;
reg [31:0] IF_ID_pc=0;

reg [31:0] ID_EX_pc=0;
reg [31:0] ID_EX_rs1_val=0;
reg [31:0] ID_EX_rs2_val=0;
reg [4:0] ID_EX_rs1=0;
reg [4:0] ID_EX_rs2=0;
reg [4:0] ID_EX_rd=0;
reg [31:0] ID_EX_imm=0;

reg ID_EX_reg_write=0;
reg ID_EX_mem_read=0;
reg ID_EX_mem_write=0;
reg ID_EX_use_imm=0;
reg ID_EX_branch=0;

reg [3:0] ID_EX_alu_op=0;

reg [31:0] EX_MEM_result=0;
reg [31:0] EX_MEM_rs2_val=0;
reg [4:0] EX_MEM_rd=0;
reg EX_MEM_reg_write=0;
reg EX_MEM_mem_read=0;
reg EX_MEM_mem_write=0;

reg [31:0] MEM_WB_result=0;
reg [4:0] MEM_WB_rd=0;
reg MEM_WB_reg_write=0;

always @(posedge clk) begin
IF_ID_instr <= imem[pc[9:2]];
IF_ID_pc <= pc;
end

wire [6:0] opcode = IF_ID_instr[6:0];
wire [2:0] funct3 = IF_ID_instr[14:12];
wire [6:0] funct7 = IF_ID_instr[31:25];

wire [4:0] rs1 = IF_ID_instr[19:15];
wire [4:0] rs2 = IF_ID_instr[24:20];
wire [4:0] rd  = IF_ID_instr[11:7];

wire [31:0] imm_i = {{20{IF_ID_instr[31]}},IF_ID_instr[31:20]};
wire [31:0] imm_s = {{20{IF_ID_instr[31]}},IF_ID_instr[31:25],IF_ID_instr[11:7]};
wire [31:0] imm_b = {{19{IF_ID_instr[31]}},IF_ID_instr[31],IF_ID_instr[7],IF_ID_instr[30:25],IF_ID_instr[11:8],1'b0};
wire [31:0] imm_j = {{11{IF_ID_instr[31]}},IF_ID_instr[31],IF_ID_instr[19:12],IF_ID_instr[20],IF_ID_instr[30:21],1'b0};

wire [31:0] rs1_data = regs[rs1];
wire [31:0] rs2_data = regs[rs2];

reg reg_write;
reg mem_read;
reg mem_write;
reg use_imm;
reg branch;
reg [3:0] alu_op;

always @(*) begin

reg_write=0;
mem_read=0;
mem_write=0;
use_imm=0;
branch=0;
alu_op=0;

case(opcode)

7'b0110011: begin
reg_write=1;

case(funct3)
3'b000: begin
if(funct7==7'b0100000) alu_op=1;
else alu_op=0;
end
3'b111: alu_op=2;
3'b110: alu_op=3;
3'b100: alu_op=4;
3'b010: alu_op=5;
endcase
end

7'b0010011: begin
reg_write=1;
use_imm=1;
alu_op=0;
end

7'b0000011: begin
reg_write=1;
mem_read=1;
use_imm=1;
alu_op=0;
end

7'b0100011: begin
mem_write=1;
use_imm=1;
alu_op=0;
end

7'b1100011: begin
branch=1;
alu_op=1;
end

7'b1101111: begin
reg_write=1;
end

7'b1100111: begin
reg_write=1;
use_imm=1;
end

endcase

end

always @(posedge clk) begin

ID_EX_pc <= IF_ID_pc;
ID_EX_rs1_val <= rs1_data;
ID_EX_rs2_val <= rs2_data;
ID_EX_rs1 <= rs1;
ID_EX_rs2 <= rs2;
ID_EX_rd <= rd;

ID_EX_reg_write <= reg_write;
ID_EX_mem_read <= mem_read;
ID_EX_mem_write <= mem_write;
ID_EX_use_imm <= use_imm;
ID_EX_branch <= branch;
ID_EX_alu_op <= alu_op;

if(opcode==7'b0100011)
ID_EX_imm <= imm_s;
else if(opcode==7'b1100011)
ID_EX_imm <= imm_b;
else
ID_EX_imm <= imm_i;

end

wire forwardA_ex = (EX_MEM_reg_write && EX_MEM_rd!=0 && EX_MEM_rd==ID_EX_rs1);
wire forwardB_ex = (EX_MEM_reg_write && EX_MEM_rd!=0 && EX_MEM_rd==ID_EX_rs2);

wire forwardA_mem = (MEM_WB_reg_write && MEM_WB_rd!=0 && MEM_WB_rd==ID_EX_rs1);
wire forwardB_mem = (MEM_WB_reg_write && MEM_WB_rd!=0 && MEM_WB_rd==ID_EX_rs2);

reg [31:0] operandA;
reg [31:0] operandB;

always @(*) begin

operandA = ID_EX_rs1_val;
operandB = ID_EX_rs2_val;

if(forwardA_ex) operandA = EX_MEM_result;
if(forwardB_ex) operandB = EX_MEM_result;

if(forwardA_mem) operandA = MEM_WB_result;
if(forwardB_mem) operandB = MEM_WB_result;

if(ID_EX_use_imm)
operandB = ID_EX_imm;

end

reg [31:0] alu_result;

always @(*) begin

case(ID_EX_alu_op)

0: alu_result = operandA + operandB;
1: alu_result = operandA - operandB;
2: alu_result = operandA & operandB;
3: alu_result = operandA | operandB;
4: alu_result = operandA ^ operandB;
5: alu_result = (operandA < operandB);

default: alu_result = 0;

endcase

end

wire branch_taken = ID_EX_branch && (operandA==operandB);
wire [31:0] branch_target = ID_EX_pc + ID_EX_imm;

always @(posedge clk) begin

if(branch_taken)
pc <= branch_target;
else
pc <= pc + 4;

end

always @(posedge clk) begin

EX_MEM_result <= alu_result;
EX_MEM_rs2_val <= ID_EX_rs2_val;
EX_MEM_rd <= ID_EX_rd;

EX_MEM_reg_write <= ID_EX_reg_write;
EX_MEM_mem_read <= ID_EX_mem_read;
EX_MEM_mem_write <= ID_EX_mem_write;

end

reg [31:0] mem_data=0;

always @(posedge clk) begin

if(EX_MEM_mem_write)
dmem[EX_MEM_result[9:2]] <= EX_MEM_rs2_val;

if(EX_MEM_mem_read)
mem_data <= dmem[EX_MEM_result[9:2]];

end

always @(posedge clk) begin

if(EX_MEM_mem_read)
MEM_WB_result <= mem_data;
else
MEM_WB_result <= EX_MEM_result;

MEM_WB_rd <= EX_MEM_rd;
MEM_WB_reg_write <= EX_MEM_reg_write;

end

always @(posedge clk) begin

if(MEM_WB_reg_write && MEM_WB_rd!=0)
regs[MEM_WB_rd] <= MEM_WB_result;

end

endmodule

sim/cpu_pipeline_tb.v
`timescale 1ns/1ps

module cpu_pipeline_tb;

reg clk;

cpu_pipeline uut(
    .clk(clk)
);

always #5 clk = ~clk;

initial begin

$dumpfile("cpu_pipeline.vcd");
$dumpvars(0,cpu_pipeline_tb);

clk = 0;

/////////////////////////////////////////////////
// PROGRAM
/////////////////////////////////////////////////

// ADDI x1, x0, 5
uut.imem[0] = 32'h00500093;

// ADDI x2, x0, 7
uut.imem[1] = 32'h00700113;

// SW x2,0(x1)
uut.imem[2] = 32'h0020A023;

// LW x3,0(x1)
uut.imem[3] = 32'h0000A183;

// ADD x4,x2,x3
uut.imem[4] = 32'h00310233;

// BEQ x4,x3,8
uut.imem[5] = 32'h00320463;

// ADDI x5,1
uut.imem[6] = 32'h00100293;

// ADDI x6,9
uut.imem[7] = 32'h00900313;

/////////////////////////////////////////////////

#200;

$finish;

end

endmodule

cpu_pipeline.vcd
$date
	Wed Mar  4 18:53:24 2026
$end
$version
	Icarus Verilog
$end
$timescale
	1ps
$end
$scope module cpu_pipeline_tb $end
$var reg 1 ! clk $end
$scope module uut $end
$var wire 1 " branch_taken $end
$var wire 1 ! clk $end
$var wire 1 # forwardA_ex $end
$var wire 1 $ forwardA_mem $end
$var wire 1 % forwardB_ex $end
$var wire 1 & forwardB_mem $end
$var wire 32 ' rs1_data [31:0] $end
$var wire 32 ( rs2_data [31:0] $end
$var wire 5 ) rs2 [4:0] $end
$var wire 5 * rs1 [4:0] $end
$var wire 5 + rd [4:0] $end
$var wire 7 , opcode [6:0] $end
$var wire 32 - imm_s [31:0] $end
$var wire 32 . imm_j [31:0] $end
$var wire 32 / imm_i [31:0] $end
$var wire 32 0 imm_b [31:0] $end
$var wire 7 1 funct7 [6:0] $end
$var wire 3 2 funct3 [2:0] $end
$var wire 32 3 branch_target [31:0] $end
$var reg 1 4 EX_MEM_mem_read $end
$var reg 1 5 EX_MEM_mem_write $end
$var reg 5 6 EX_MEM_rd [4:0] $end
$var reg 1 7 EX_MEM_reg_write $end
$var reg 32 8 EX_MEM_result [31:0] $end
$var reg 32 9 EX_MEM_rs2_val [31:0] $end
$var reg 4 : ID_EX_alu_op [3:0] $end
$var reg 1 ; ID_EX_branch $end
$var reg 32 < ID_EX_imm [31:0] $end
$var reg 1 = ID_EX_mem_read $end
$var reg 1 > ID_EX_mem_write $end
$var reg 32 ? ID_EX_pc [31:0] $end
$var reg 5 @ ID_EX_rd [4:0] $end
$var reg 1 A ID_EX_reg_write $end
$var reg 5 B ID_EX_rs1 [4:0] $end
$var reg 32 C ID_EX_rs1_val [31:0] $end
$var reg 5 D ID_EX_rs2 [4:0] $end
$var reg 32 E ID_EX_rs2_val [31:0] $end
$var reg 1 F ID_EX_use_imm $end
$var reg 32 G IF_ID_instr [31:0] $end
$var reg 32 H IF_ID_pc [31:0] $end
$var reg 5 I MEM_WB_rd [4:0] $end
$var reg 1 J MEM_WB_reg_write $end
$var reg 32 K MEM_WB_result [31:0] $end
$var reg 4 L alu_op [3:0] $end
$var reg 32 M alu_result [31:0] $end
$var reg 1 N branch $end
$var reg 32 O mem_data [31:0] $end
$var reg 1 P mem_read $end
$var reg 1 Q mem_write $end
$var reg 32 R operandA [31:0] $end
$var reg 32 S operandB [31:0] $end
$var reg 32 T pc [31:0] $end
$var reg 1 U reg_write $end
$var reg 1 V use_imm $end
$var integer 32 W i [31:0] $end
$var integer 32 X j [31:0] $end
$upscope $end
$upscope $end
$enddefinitions $end
$comment Show the parameter values. $end
$dumpall
$end
#0
$dumpvars
b100000000 X
b100000 W
0V
0U
b0 T
b0 S
b0 R
0Q
0P
b0 O
0N
b0 M
b0 L
b0 K
0J
b0 I
b0 H
b0 G
0F
b0 E
b0 D
b0 C
b0 B
0A
b0 @
b0 ?
0>
0=
b0 <
0;
b0 :
b0 9
b0 8
07
b0 6
05
04
b0 3
b0 2
b0 1
b0 0
b0 /
b0 .
b0 -
b0 ,
b0 +
b0 *
b0 )
b0 (
b0 '
0&
0%
0$
0#
0"
0!
$end
#5000
1V
1U
b10011 ,
b101 )
b1 +
b101 /
b1 -
b100000000000 0
b100000000100 .
b10100000000000010010011 G
b100 T
1!
#10000
0!
#15000
b101 M
b101 S
b111 )
b10 +
b111 /
b10 -
b10 0
b100000000110 .
b1000 T
b101 3
b101 <
1F
1A
b1 @
b101 D
b100 H
b11100000000000100010011 G
1!
#20000
0!
#25000
1Q
1V
0U
b111 M
b100011 ,
b10 2
b1 *
b10 )
b0 +
b10 /
b0 -
b0 0
b1010000000000010 .
b111 S
b1000 H
b1000001010000000100011 G
b111 <
b10 @
b111 D
b1011 3
b100 ?
b1100 T
17
b1 6
b101 8
1!
#30000
0!
#35000
b101 R
1$
b101 M
1P
1U
1V
0Q
1%
b0 S
b11 ,
b0 )
b11 +
b0 /
b11 -
b100000000010 0
b1010000000000000 .
1J
b1 I
b101 K
b10 6
b111 8
b10000 T
b0 <
1>
0A
b0 @
b10 D
b1 B
b1000 3
b1000 ?
b1100 H
b1010000110000011 G
1!
#40000
0!
#45000
0V
0P
1U
0%
b0 M
b110011 ,
b0 2
b10 *
b11 )
b100 +
b11 /
b100 -
b100 0
b10000100000000010 .
0$
b0 S
b0 R
b10000 H
b1100010000001000110011 G
0>
1=
1A
b11 @
b0 D
b1100 3
b1100 ?
b10100 T
15
07
b0 6
b101 8
b10 I
b111 K
b0 '
1!
#50000
0!
#55000
1%
b1 L
1N
0U
b1100011 ,
b100 *
b1000 +
b1000 -
b1000 0
b100000100000000010 .
b0 '
0J
b0 I
b101 K
05
14
17
b11 6
b0 8
b11000 T
b11 <
0F
0=
b100 @
b11 D
b10 B
b10011 3
b10000 ?
b10100 H
b1100100000010001100011 G
1!
#60000
0!
#65000
1V
1U
b0 L
0N
1&
b10011 ,
b0 *
b101 (
b1 )
b101 +
b1 /
b101 -
b100000000100 0
b100000000000 .
1"
1#
0%
b11000 H
b100000000001010010011 G
b1000 <
b1 :
1;
0A
b1000 @
b100 B
b11100 3
b10100 ?
b11100 T
04
b100 6
1J
b11 I
b0 K
1!
#70000
0!
#75000
b1 M
0"
0&
0#
b1 S
b0 (
b1001 )
b110 +
b1001 /
b110 -
b110 0
b100000001000 .
b100 I
07
b1000 6
b1 <
b0 :
0;
1F
1A
b101 @
b1 D
b0 B
b101 E
b11001 3
b11000 ?
b11100 H
b100100000000001100010011 G
1!
#80000
0!
#85000
b1001 M
b1001 S
b1001 <
b110 @
b1001 D
b0 E
b100101 3
b11100 ?
b100000 T
17
b101 6
b101 9
b1 8
0J
b1000 I
1!
#90000
0!
#95000
0V
0U
b1001 S
bx ,
bx 2
bx 1
bx '
bx *
bx (
bx )
bx +
bx /
bx -
bx0 0
bx0 .
1J
b101 I
b1 K
b110 6
b0 9
b1001 8
b100100 T
b100000 H
bx G
1!
#100000
0!
#105000
bx M
x%
x&
x#
x$
bx S
bx R
b100100 H
bx <
0F
0A
bx @
bx D
bx B
bx E
bx C
bx 3
b100000 ?
b101000 T
b110 I
b1001 K
1!
#110000
0!
#115000
0#
0%
07
bx 6
bx 9
bx 8
b101100 T
b100100 ?
b101000 H
1!
#120000
0!
#125000
0$
0&
b101100 H
b101000 ?
b110000 T
0J
bx I
bx K
1!
#130000
0!
#135000
b110100 T
b101100 ?
b110000 H
1!
#140000
0!
#145000
b110100 H
b110000 ?
b111000 T
1!
#150000
0!
#155000
b111100 T
b110100 ?
b111000 H
1!
#160000
0!
#165000
b111100 H
b111000 ?
b1000000 T
1!
#170000
0!
#175000
b1000100 T
b111100 ?
b1000000 H
1!
#180000
0!
#185000
b1000100 H
b1000000 ?
b1001000 T
1!
#190000
0!
#195000
b1001100 T
b1000100 ?
b1001000 H
1!
